pymobilecode/MobileCode.py
pymobilecode/__init__.py
pymobilecode_shaw1236-0.0.2.dist-info/LICENSE
pymobilecode_shaw1236-0.0.2.dist-info/METADATA
pymobilecode_shaw1236-0.0.2.dist-info/WHEEL
pymobilecode_shaw1236-0.0.2.dist-info/top_level.txt
pymobilecode_shaw1236-0.0.2.dist-info/RECORD
